{"id1":43872,"id2":43922,"matches":[{"idHomeTeam":43872,"idAwayTeam":43922,"matchDate":"2004-04-29 01:00:00","scoreHome":0,"scoreAway":1,"venueName":"Casablanca ","scorePenaltyAway":0,"scorePenaltyHome":0,"reasonWinCode":0,"rHpoints":686,"rApoints":1254,"cupKindID":105,"name":"Friendlies","deliveryDateHome":"2004-05-12 00:00:00","rankseqHome":32,"deliveryDateAway":"2004-05-12 00:00:00","rankseqAway":5},{"idHomeTeam":43922,"idAwayTeam":43872,"matchDate":"1994-04-21 02:00:00","scoreHome":3,"scoreAway":1,"venueName":"Salta ","scorePenaltyAway":0,"scorePenaltyHome":0,"reasonWinCode":0,"rHpoints":1254,"rApoints":686,"cupKindID":105,"name":"Friendlies","deliveryDateHome":"1994-04-19 00:00:00","rankseqHome":10,"deliveryDateAway":"1994-04-19 00:00:00","rankseqAway":26}]}