{"id1":43901,"id2":43929,"matches":[{"idHomeTeam":43901,"idAwayTeam":43929,"matchDate":"2012-08-15 02:00:00","scoreHome":0,"scoreAway":1,"venueName":"San Jose ","scorePenaltyAway":0,"scorePenaltyHome":0,"reasonWinCode":0,"rHpoints":884,"rApoints":1125,"cupKindID":105,"name":"Friendlies","deliveryDateHome":"2012-08-08 00:00:00","rankseqHome":62,"deliveryDateAway":"2012-08-08 00:00:00","rankseqAway":47},{"idHomeTeam":43929,"idAwayTeam":43901,"matchDate":"2010-10-08 23:00:00","scoreHome":2,"scoreAway":0,"venueName":"Lima ","scorePenaltyAway":0,"scorePenaltyHome":0,"reasonWinCode":0,"rHpoints":1125,"rApoints":884,"cupKindID":105,"name":"Friendlies","deliveryDateHome":"2010-10-20 00:00:00","rankseqHome":55,"deliveryDateAway":"2010-10-20 00:00:00","rankseqAway":66},{"idHomeTeam":43929,"idAwayTeam":43901,"matchDate":"2008-03-26 01:00:00","scoreHome":3,"scoreAway":1,"venueName":"Iquitos ","scorePenaltyAway":0,"scorePenaltyHome":0,"reasonWinCode":0,"rHpoints":1125,"rApoints":884,"cupKindID":105,"name":"Friendlies","deliveryDateHome":"2008-04-09 00:00:00","rankseqHome":64,"deliveryDateAway":"2008-04-09 00:00:00","rankseqAway":75},{"idHomeTeam":43901,"idAwayTeam":43929,"matchDate":"2007-08-22 22:00:00","scoreHome":1,"scoreAway":1,"venueName":"San Juan ","scorePenaltyAway":0,"scorePenaltyHome":0,"reasonWinCode":0,"rHpoints":884,"rApoints":1125,"cupKindID":105,"name":"Friendlies","deliveryDateHome":"2007-08-22 00:00:00","rankseqHome":52,"deliveryDateAway":"2007-08-22 00:00:00","rankseqAway":54},{"idHomeTeam":43929,"idAwayTeam":43901,"matchDate":"1996-08-14 22:45:00","scoreHome":3,"scoreAway":0,"venueName":"Arequipa ","scorePenaltyAway":0,"scorePenaltyHome":0,"reasonWinCode":0,"rHpoints":1125,"rApoints":884,"cupKindID":105,"name":"Friendlies","deliveryDateHome":"1996-08-28 00:00:00","rankseqHome":66,"deliveryDateAway":"1996-08-28 00:00:00","rankseqAway":85},{"idHomeTeam":43929,"idAwayTeam":43901,"matchDate":"1956-03-17 01:00:00","scoreHome":2,"scoreAway":4,"venueName":"Mexico City ","scorePenaltyAway":0,"scorePenaltyHome":0,"reasonWinCode":0,"rHpoints":1125,"rApoints":884,"cupKindID":105,"name":"Friendlies","deliveryDateHome":"1992-12-31 00:00:00","rankseqHome":78,"deliveryDateAway":"1992-12-31 00:00:00","rankseqAway":37}]}