{"id1":43963,"id2":43930,"matches":[{"idHomeTeam":43963,"idAwayTeam":43930,"matchDate":"1972-07-02 01:00:00","scoreHome":1,"scoreAway":1,"venueName":"Rio De Janeiro ","scorePenaltyAway":0,"scorePenaltyHome":0,"reasonWinCode":0,"rHpoints":1306,"rApoints":1018,"cupKindID":105,"name":"Friendlies","deliveryDateHome":"1992-12-31 00:00:00","rankseqHome":33,"deliveryDateAway":"1992-12-31 00:00:00","rankseqAway":16},{"idHomeTeam":43963,"idAwayTeam":43930,"matchDate":"1966-06-26 02:00:00","scoreHome":3,"scoreAway":0,"venueName":"Lisbon ","scorePenaltyAway":0,"scorePenaltyHome":0,"reasonWinCode":0,"rHpoints":1306,"rApoints":1018,"cupKindID":105,"name":"Friendlies","deliveryDateHome":"1992-12-31 00:00:00","rankseqHome":33,"deliveryDateAway":"1992-12-31 00:00:00","rankseqAway":16}]}