{"id1":43965,"id2":43969,"matches":[{"idHomeTeam":43965,"idAwayTeam":43969,"matchDate":"2017-11-14 22:45:00","scoreHome":3,"scoreAway":3,"venueName":"St. Petersburg ","scorePenaltyAway":0,"scorePenaltyHome":0,"reasonWinCode":0,"rHpoints":493,"rApoints":1162,"cupKindID":105,"name":"Friendlies","deliveryDateHome":"2017-11-23 00:00:00","rankseqHome":65,"deliveryDateAway":"2017-11-23 00:00:00","rankseqAway":6},{"idHomeTeam":43965,"idAwayTeam":43969,"matchDate":"2008-06-26 21:45:00","scoreHome":0,"scoreAway":3,"venueName":"Vienna ","scorePenaltyAway":0,"scorePenaltyHome":0,"reasonWinCode":0,"rHpoints":493,"rApoints":1162,"cupKindID":102,"name":"UEFA EURO 2008","deliveryDateHome":"2008-07-02 00:00:00","rankseqHome":11,"deliveryDateAway":"2008-07-02 00:00:00","rankseqAway":1},{"idHomeTeam":43969,"idAwayTeam":43965,"matchDate":"2008-06-10 18:00:00","scoreHome":4,"scoreAway":1,"venueName":"Innsbruck ","scorePenaltyAway":0,"scorePenaltyHome":0,"reasonWinCode":0,"rHpoints":1162,"rApoints":493,"cupKindID":102,"name":"UEFA EURO 2008","deliveryDateHome":"2008-06-04 00:00:00","rankseqHome":4,"deliveryDateAway":"2008-06-04 00:00:00","rankseqAway":24},{"idHomeTeam":43969,"idAwayTeam":43965,"matchDate":"2006-05-27 02:00:00","scoreHome":0,"scoreAway":0,"venueName":"Albacete ","scorePenaltyAway":0,"scorePenaltyHome":0,"reasonWinCode":0,"rHpoints":1162,"rApoints":493,"cupKindID":105,"name":"Friendlies","deliveryDateHome":"2006-05-17 00:00:00","rankseqHome":5,"deliveryDateAway":"2006-05-17 00:00:00","rankseqAway":37},{"idHomeTeam":43969,"idAwayTeam":43965,"matchDate":"2004-06-12 21:45:00","scoreHome":1,"scoreAway":0,"venueName":"Faro-Loule ","scorePenaltyAway":0,"scorePenaltyHome":0,"reasonWinCode":0,"rHpoints":1162,"rApoints":493,"cupKindID":102,"name":"UEFA EURO 2004","deliveryDateHome":"2004-06-09 00:00:00","rankseqHome":3,"deliveryDateAway":"2004-06-09 00:00:00","rankseqAway":31},{"idHomeTeam":43969,"idAwayTeam":43965,"matchDate":"1998-09-23 23:45:00","scoreHome":1,"scoreAway":0,"venueName":"Granada ","scorePenaltyAway":0,"scorePenaltyHome":0,"reasonWinCode":0,"rHpoints":1162,"rApoints":493,"cupKindID":105,"name":"Friendlies","deliveryDateHome":"1998-09-16 00:00:00","rankseqHome":14,"deliveryDateAway":"1998-09-16 00:00:00","rankseqAway":27}]}